{"data":{"names":[{"dateOfBirth":"16 January 1957","placeOfBirth":" Autonomous City of Buenos Aires, Argentina","birthName":"Ricardo Alberto Darín","height":"5' 7¾\" (1.72 m)","bio":"Ricardo Darín was born in Buenos Aires, Argentina, on January 16, 1957. He works since he was a little boy, and has obtained with the years a remarkable evolution from soap opera gallant and tv comedies to an excellent leading figure of the most importants Argentinian movies. At the age of 10 he made his debut in a play along with his parents, actor Ricardo Darín Sr., and actess Renée Roxana. He acted for several years in TV series (such as Alta Comedia and Estación Retiro), where he reached popularity as a young leading actor in different soap operas, specially in Alberto Migre's productions. In the 90s, he achieved a great success in the TV comedy \"Mi Cuñado\" (1993), in which he co-starred with Luis Brandoni. He never left theater and continued acting in plays like \"Sugar\", \"Extraña Pareja\", \"Taxi\", \"Algo en Común\" and \"Art\". At that time, he directed plays and movies like \"He nacido en la ribera\", \"La Rabona\" y \"Los Exitos del Amor\". The first time the critic emphasized his performance was in the movie \"Perdido por Perdido\" (1993), Alberto Lecchi's debut as a film director. Then, he played in \"El Faro\" (1998), \"El Mismo Amor La Misma Lluvia\" (1999), and \"Nueve Reinas\" (2000), brilliantly portraying Marcos. Once again, he colaborated with director Eduardo Mignona when he portrayed Domingo Santaló in \"La Fuga\" (2001). In 2001 he played Rafael Belvedere in \"El Hijo de la Novia\" (nominated in the foreign language category at the 2002 Oscars), crowning his career. Currently (2005), he is on tour with the play \"Art\" all over the world. He lives with his wife, Florencia Bas, and his children, Ricardo Jr. and Clara.","urlPhoto":"https://images-na.ssl-images-amazon.com/images/M/MV5BMTgxOTAyMTAzNV5BMl5BanBnXkFtZTcwODE2MTUzOA@@._V1.jpg","urlIMDB":"http://www.imdb.com/name/nm0201857","name":"Ricardo Darín","nicknames":["Richard"],"idIMDB":"nm0201857","filmographies":[{"section":"Actor","filmography":[{"title":"The Summit","year":" 2017","remarks":null,"imdbid":"tt6047298"},{"title":"Nieve negra","year":" 2017","remarks":null,"imdbid":"tt5614612"},{"title":"Black or White, Never Gray","year":" ","remarks":["(TV Series)"],"imdbid":"tt3228684"},{"title":"Koblic","year":" 2016","remarks":null,"imdbid":"tt5462400"},{"title":"Truman","year":" 2015","remarks":["Julián (as Ricardo Darin)"],"imdbid":"tt3754940"},{"title":"Torrente 5","year":" 2014","remarks":["Comandante Cudilleros (as Ricardo)"],"imdbid":"tt3321428"},{"title":"La chica más rara del mundo","year":" 2014","remarks":["(Short)"],"imdbid":"tt3954804"},{"title":"Les nouveaux sauvages","year":" 2014","remarks":["Simón (segment \"Bombita\")"],"imdbid":"tt3011894"},{"title":"Violet","year":" 2013/I","remarks":null,"imdbid":"tt2377398"},{"title":"7th Floor","year":" 2013","remarks":null,"imdbid":"tt2403961"},{"title":"Hipotesis","year":" 2013","remarks":null,"imdbid":"tt2241605"},{"title":"Les hommes! De quoi parlent-ils?","year":" 2012","remarks":null,"imdbid":"tt1945034"},{"title":"Elefante blanco","year":" 2012","remarks":null,"imdbid":"tt2132324"},{"title":"En fuera de juego","year":" 2011","remarks":["Coco (uncredited)"],"imdbid":"tt1760958"},{"title":"Chinese Take-Out","year":" 2011","remarks":null,"imdbid":"tt1705786"},{"title":"Carancho","year":" 2010","remarks":null,"imdbid":"tt1542852"},{"title":"Para vestir santos","year":" 2010","remarks":["(TV Mini-Series)"],"imdbid":"tt1645536"},{"title":"The Dancer and the Thief","year":" 2009","remarks":null,"imdbid":"tt1243375"},{"title":"The Secret in Their Eyes","year":" 2009","remarks":null,"imdbid":"tt1305806"},{"title":"Lovely Loneliness","year":" 2008","remarks":null,"imdbid":"tt1160004"},{"title":"La señal","year":" 2007","remarks":null,"imdbid":"tt0906777"},{"title":"XXY","year":" 2007","remarks":null,"imdbid":"tt0995829"},{"title":"Hoy me desperté","year":" 2006","remarks":["(TV Movie)"],"imdbid":"tt5243492"},{"title":"L'éducation d'une fée","year":" 2006","remarks":null,"imdbid":"tt0485634"},{"title":"El amor a las cuatro de la tarde","year":" 2005","remarks":["(Short)","Narrador (voice)"],"imdbid":"tt0486083"},{"title":"The Aura","year":" 2005","remarks":null,"imdbid":"tt0420509"},{"title":"Avellaneda's Moon","year":" 2004","remarks":null,"imdbid":"tt0347449"},{"title":"Kamchatka","year":" 2002","remarks":null,"imdbid":"tt0320042"},{"title":"Sammy and Me","year":" 2002","remarks":null,"imdbid":"tt0293567"},{"title":"Porque te quiero","year":" 2001","remarks":null,"imdbid":"tt0283556"},{"title":"Son of the Bride","year":" 2001","remarks":null,"imdbid":"tt0292542"},{"title":"La fuga","year":" 2001","remarks":null,"imdbid":"tt0281870"},{"title":"Nine Queens","year":" 2000","remarks":null,"imdbid":"tt0247586"},{"title":"Final Minute","year":" 2000","remarks":["(TV Mini-Series)"],"imdbid":"tt0259160"},{"title":"Por ese palpitar","year":" 2000","remarks":["(TV Series)"],"imdbid":"tt0258368"},{"title":"El mismo amor, la misma lluvia","year":" 1999","remarks":null,"imdbid":"tt0210843"},{"title":"La mujer del presidente","year":" 1999","remarks":["(TV Series)"],"imdbid":"tt0222216"},{"title":"The Lighthouse","year":" 1998","remarks":["Andy (as Ricardo Darin)"],"imdbid":"tt0168749"},{"title":"Chiquititas","year":" 1998","remarks":["(TV Series)"],"imdbid":"tt0154063"},{"title":"Perdido por perdido","year":" 1993","remarks":null,"imdbid":"tt0107805"},{"title":"Mi cuñado","year":" 1993","remarks":["(TV Series)"],"imdbid":"tt0220246"},{"title":"Mi otro yo","year":" 1992","remarks":["(TV Series)"],"imdbid":"tt5168230"},{"title":"Buenos Aires háblame de amor","year":" 1991","remarks":["(TV Series)"],"imdbid":"tt0267156"},{"title":"Rebelde","year":" 1989","remarks":["(TV Series)"],"imdbid":"tt0224954"},{"title":"The Stranger","year":" 1987","remarks":null,"imdbid":"tt0137291"},{"title":"Revancha de un amigo","year":" 1987","remarks":null,"imdbid":"tt0311716"},{"title":"Estrellita mía","year":" 1987","remarks":["(TV Series)"],"imdbid":"tt0199213"},{"title":"Te amo","year":" 1986","remarks":null,"imdbid":"tt0320576"},{"title":"Les longs manteaux","year":" 1986","remarks":null,"imdbid":"tt0091429"},{"title":"La rosales","year":" 1984","remarks":null,"imdbid":"tt0121702"},{"title":"Galas de teatro","year":" 1984","remarks":["(TV Mini-Series)"],"imdbid":"tt5008474"},{"title":"Historia de un trepador","year":" 1984","remarks":["(TV Series)"],"imdbid":"tt0224888"},{"title":"Los exclusivos del 11","year":" 1984","remarks":["(TV Series)"],"imdbid":"tt5004782"},{"title":"Deadly Revenge","year":" 1983","remarks":null,"imdbid":"tt0085411"},{"title":"Compromiso","year":" 1983","remarks":["(TV Series)"],"imdbid":"tt0354281"},{"title":"Juan sin nombre","year":" 1982","remarks":["(TV Series)"],"imdbid":"tt0222576"},{"title":"Nosotros y los miedos","year":" 1982","remarks":["(TV Series)"],"imdbid":"tt0353085"},{"title":"Fiesta de aniversario de Canal 9","year":" 1981","remarks":["(TV Movie)"],"imdbid":"tt4932674"},{"title":"Abierto día y noche","year":" 1981","remarks":null,"imdbid":"tt0179066"},{"title":"Me caso con vos","year":" 1981","remarks":["(TV Series)"],"imdbid":"tt0277494"},{"title":"The Disco of Love","year":" 1980","remarks":null,"imdbid":"tt0080633"},{"title":"La canción de Buenos Aires","year":" 1980","remarks":null,"imdbid":"tt0200516"},{"title":"La playa del amor","year":" 1980","remarks":null,"imdbid":"tt0081343"},{"title":"Casa de muñecas","year":" 1980","remarks":["(TV Mini-Series)"],"imdbid":"tt0498422"},{"title":"Un día 32 en San Telmo","year":" 1980","remarks":["(TV Series)"],"imdbid":"tt0292783"},{"title":"Juventud sin barreras","year":" 1979","remarks":null,"imdbid":"tt0301495"},{"title":"La carpa del amor","year":" 1979","remarks":null,"imdbid":"tt0194738"},{"title":"La rabona","year":" 1979","remarks":null,"imdbid":"tt0191390"},{"title":"Los éxitos del amor","year":" 1979","remarks":null,"imdbid":"tt0201372"},{"title":"Una escalera al cielo","year":" 1979","remarks":["(TV Series)"],"imdbid":"tt0224871"},{"title":"Vos y yo, toda la vida","year":" 1978","remarks":["(TV Series)"],"imdbid":"tt0265003"},{"title":"La nueva cigarra","year":" 1977","remarks":null,"imdbid":"tt0074982"},{"title":"Such Is Life","year":" 1977","remarks":null,"imdbid":"tt0178246"},{"title":"El tema es el amor","year":" 1977","remarks":["(TV Series)"],"imdbid":"tt0373631"},{"title":"Ayer fue mentira","year":" 1975","remarks":["(TV Series)"],"imdbid":"tt0363317"},{"title":"La familia Super Star","year":" 1975","remarks":["(TV Series)"],"imdbid":"tt4932694"},{"title":"He nacido en la ribera","year":" 1972","remarks":null,"imdbid":"tt0183155"},{"title":"Alta comedia","year":" 1971","remarks":["(TV Series)"],"imdbid":"tt0373476"},{"title":"Las grandes novelas","year":" 1971","remarks":["(TV Series)"],"imdbid":"tt4940470"},{"title":"La culpa","year":" 1969","remarks":null,"imdbid":"tt0178359"},{"title":"Abelardo Pardales","year":" 1969","remarks":["(TV Series)"],"imdbid":"tt0332839"},{"title":"Testimonios de hoy... Autores argentinos","year":" 1968","remarks":["(TV Series)"],"imdbid":"tt5066020"},{"title":"Soledad Monsalvo","year":" 1960","remarks":["(TV Series)"],"imdbid":"tt2289389"}]},{"section":"Director","filmography":[{"title":"La señal","year":" 2007","remarks":null,"imdbid":"tt0906777"}]},{"section":"Self","filmography":[{"title":"Susana Giménez","year":" 2007-2016","remarks":["(TV Series)"],"imdbid":"tt0227958"},{"title":"Días de cine","year":" 2009-2016","remarks":["(TV Series)"],"imdbid":"tt0390699"},{"title":"Cinema 3","year":" 2009-2016","remarks":["(TV Series)"],"imdbid":"tt0111920"},{"title":"Late Motiv de Andreu Buenafuente","year":" 2016","remarks":["(TV Series)"],"imdbid":"tt5863358"},{"title":"El informante","year":" 2016","remarks":["(TV Series)"],"imdbid":"tt5212806"},{"title":"10 años con Bebe","year":" 2016","remarks":["(Documentary)"],"imdbid":"tt5268896"},{"title":"Morfi, todos a la mesa","year":" 2016","remarks":["(TV Series)"],"imdbid":"tt4799472"},{"title":"Almorzando con Mirtha Legrand","year":" 2000-2016","remarks":["(TV Series)"],"imdbid":"tt0120919"},{"title":"Premios Goya 30 edición","year":" 2016","remarks":["(TV Movie)"],"imdbid":"tt5306836"},{"title":"VIII Premis Gaudí de l'Acadèmia del Cinema Català","year":" 2016","remarks":["(TV Movie)","Himself - Winner: Best Male Lead (video)"],"imdbid":"tt5426262"},{"title":"AM - Antes del mediodía","year":" 2011-2015","remarks":["(TV Series)"],"imdbid":"tt1271991"},{"title":"Nunca es tarde","year":" 2015","remarks":["(TV Series)"],"imdbid":"tt4699262"},{"title":"Al rincón de pensar","year":" 2015","remarks":["(TV Series documentary)"],"imdbid":"tt5539530"},{"title":"Tria33","year":" 2015","remarks":["(TV Series)"],"imdbid":"tt4711266"},{"title":"Amigas y conocidas","year":" 2015","remarks":["(TV Series)"],"imdbid":"tt3995024"},{"title":"Festival de cine de San Sebastián - Gala de clausura","year":" 2015","remarks":["(TV Movie)"],"imdbid":"tt5112296"},{"title":"Versión española","year":" 2005-2015","remarks":["(TV Series)"],"imdbid":"tt0400051"},{"title":"Línea de tiempo","year":" 2015","remarks":["(TV Series)"],"imdbid":"tt4909394"},{"title":"Duro de domar","year":" 2015","remarks":["(TV Series)"],"imdbid":"tt0778544"},{"title":"The Last Gaucho","year":" 2015","remarks":["(TV Series documentary)"],"imdbid":"tt4433104"},{"title":"Delirium","year":" 2014/IV","remarks":null,"imdbid":"tt3778394"},{"title":"Caiga quien caiga - CQC","year":" 2004-2014","remarks":["(TV Series)"],"imdbid":"tt0199191"},{"title":"Gracias por venir, gracias por estar","year":" 2012-2014","remarks":["(TV Series)"],"imdbid":"tt3628630"},{"title":"XIX Premio Cinematográfico José María Forqué","year":" 2014","remarks":["(TV Movie)"],"imdbid":"tt3465430"},{"title":"Serrat y Sabina: el símbolo y el cuate","year":" 2013","remarks":["(Documentary)"],"imdbid":"tt3215530"},{"title":"Tiene la palabra","year":" 2013","remarks":["(TV Series)"],"imdbid":"tt4139386"},{"title":"Intrusos en el espectáculo","year":" 2013","remarks":["(TV Series)"],"imdbid":"tt0341161"},{"title":"Telenoche","year":" 2013","remarks":["(TV Series)"],"imdbid":"tt0456801"},{"title":"Pura Química","year":" 2011-2013","remarks":["(TV Series)"],"imdbid":"tt2070365"},{"title":"El ocaso del Macá Tobiano","year":" 2012","remarks":["(Documentary short)"],"imdbid":"tt2449294"},{"title":"Gala de clausura - 60 Festival Internacional de cine de San Sebastián","year":" 2012","remarks":["(TV Movie)"],"imdbid":"tt2424688"},{"title":"Ceremonia de inauguración - 60 Festival Internacional de Cine de San Sebastián","year":" 2012","remarks":["(TV Movie)"],"imdbid":"tt2408816"},{"title":"Miradas 2","year":" 2005-2012","remarks":["(TV Series documentary)"],"imdbid":"tt0454730"},{"title":"Antes que sea tarde","year":" 2012","remarks":["(TV Series)"],"imdbid":"tt2318857"},{"title":"Televisión registrada","year":" 2012","remarks":["(TV Series)"],"imdbid":"tt0341193"},{"title":"Gente","year":" 2012","remarks":["(TV Series)"],"imdbid":"tt0447759"},{"title":"Los Goya 26 edición","year":" 2012","remarks":["(TV Special)"],"imdbid":"tt2179287"},{"title":"La biblia y el calefón","year":" 2011","remarks":["(TV Series)"],"imdbid":"tt0283174"},{"title":"Premios Martín Fierro 2011","year":" 2011","remarks":["(TV Special)","Himself - Winner: Best Guest Appearance in a TV Series (credit only)"],"imdbid":"tt2124020"},{"title":"¿Qué fue de tu vida?","year":" 2011","remarks":["(TV Series)"],"imdbid":"tt1933526"},{"title":"Un mundo perfecto","year":" 2010-2011","remarks":["(TV Series)"],"imdbid":"tt1931248"},{"title":"Delirium Argentinum","year":" 2010","remarks":null,"imdbid":"tt1674053"},{"title":"Un sol para los chicos","year":" 2010","remarks":["(TV Series)"],"imdbid":"tt2011347"},{"title":"30 minuts","year":" 2010","remarks":["(TV Series documentary)"],"imdbid":"tt2294989"},{"title":"La pregunta animal","year":" 2010","remarks":["(TV Series)"],"imdbid":"tt0409606"},{"title":"Premios Clarín Espectáculos 2009","year":" 2009","remarks":["(TV Special)"],"imdbid":"tt2103258"},{"title":"El hormiguero","year":" 2009","remarks":["(TV Series)"],"imdbid":"tt0870872"},{"title":"Zoom, mirá de cerca","year":" 2009","remarks":["(TV Series)"],"imdbid":"tt1966341"},{"title":"Democracia: Crónica de la transición","year":" 2008","remarks":["(Documentary)"],"imdbid":"tt2083166"},{"title":"Mañanas informales","year":" 2005-2007","remarks":["(TV Series)"],"imdbid":"tt1990663"},{"title":"Cartelera","year":" 2007","remarks":["(TV Series)"],"imdbid":"tt0447736"},{"title":"Continuarà...","year":" 2002-2007","remarks":["(TV Series)"],"imdbid":"tt1067602"},{"title":"El club","year":" 2005-2007","remarks":["(TV Series)"],"imdbid":"tt0441917"},{"title":"La Marató 2005","year":" 2005","remarks":["(TV Special)"],"imdbid":"tt0494971"},{"title":"Buenafuente","year":" 2005","remarks":["(TV Series)"],"imdbid":"tt0442870"},{"title":"El Magacine","year":" 2005","remarks":["(TV Series)"],"imdbid":"tt0475467"},{"title":"San Sebastián 2005: Crónica de Carlos Boyero","year":" 2005","remarks":["(TV Movie)"],"imdbid":"tt0483153"},{"title":"La noche del 10","year":" 2005","remarks":["(TV Series)"],"imdbid":"tt0489614"},{"title":"La mandrágora","year":" 2005","remarks":["(TV Series)"],"imdbid":"tt0441933"},{"title":"Caiga quien caiga","year":" 2005","remarks":["(TV Series)"],"imdbid":"tt0241090"},{"title":"Las cerezas","year":" 2005","remarks":["(TV Series)"],"imdbid":"tt0431514"},{"title":"La noche abierta","year":" 2003","remarks":["(TV Series)"],"imdbid":"tt0371468"},{"title":"Una altra cosa","year":" 2003","remarks":["(TV Series)"],"imdbid":"tt0390787"},{"title":"Toni Rovira y tú","year":" 2003","remarks":["(TV Series)"],"imdbid":"tt1479130"},{"title":"Haz el humor y no la guerra","year":" 2003","remarks":["(TV Movie)"],"imdbid":"tt1479245"},{"title":"Lo + plus","year":" 2002-2003","remarks":["(TV Series)"],"imdbid":"tt0373558"},{"title":"La noche con Fuentes y Cía","year":" 2003","remarks":["(TV Series)"],"imdbid":"tt0373582"},{"title":"Ahora","year":" 2003","remarks":["(TV Series)"],"imdbid":"tt0386910"},{"title":"Premios Clarín Espectáculos 2002","year":" 2002","remarks":["(TV Special)"],"imdbid":"tt2098830"},{"title":"Claroscuro","year":" 2000","remarks":["(Documentary short)"],"imdbid":"tt1266634"},{"title":"Versus","year":" 2000","remarks":["(TV Series)"],"imdbid":"tt0287277"},{"title":"Hola Susana","year":" 1997","remarks":["(TV Series)"],"imdbid":"tt0364168"},{"title":"Duro de acostar","year":" 1997","remarks":["(TV Series)"],"imdbid":"tt0371447"},{"title":"La fiesta de todos","year":" 1979","remarks":["(Documentary)"],"imdbid":"tt0194880"}]},{"section":"Archive footage","filmography":[{"title":"1002 Momentos de la tele","year":" 2013","remarks":["(TV Series)"],"imdbid":"tt3646334"},{"title":"Gracias por venir, gracias por estar","year":" 2012","remarks":["(TV Series)"],"imdbid":"tt3628630"},{"title":"Las tragedias de los famosos","year":" 2010","remarks":["(TV Series)"],"imdbid":"tt4911536"},{"title":"XXIV Premios Anuales de la Academia","year":" 2010","remarks":["(TV Special)"],"imdbid":"tt1562930"},{"title":"Born to Suffer","year":" 2009","remarks":null,"imdbid":"tt1309472"},{"title":"De par en par","year":" 2007","remarks":["(TV Series)"],"imdbid":"tt0989177"},{"title":"La tele de tu vida","year":" 2007","remarks":["(TV Series)"],"imdbid":"tt0943381"},{"title":"La mandrágora","year":" 2005-2006","remarks":["(TV Series)"],"imdbid":"tt0441933"},{"title":"El Magacine","year":" 2005","remarks":["(TV Series)"],"imdbid":"tt0475467"},{"title":"Aunque usted no lo viera","year":" 2005","remarks":["(TV Series)"],"imdbid":"tt0778532"},{"title":"Los nuevos y clásicos bloopers","year":" 2004","remarks":["(TV Series)"],"imdbid":"tt5607020"}]}]}]},"about":{"version":"2.26.6","serverTime":"2017/01/15 02:28:51"}}