{"data":{"names":[{"dateOfBirth":"12 June 1898","placeOfBirth":" Paris, France","bio":"Jean Témerson was born on June 12, 1898 in Paris, France. He was an actor, known for Diabolique (1955), Pépé le Moko (1937) and The Count of Monte Cristo (1954). He died on August 9, 1956 in Paris.","urlPhoto":"http://ia.media-imdb.com/images/G/01/imdb/images/nopicture/medium/name-2135195744._CB522736367_.png","urlIMDB":"http://www.imdb.com/name/nm0879400","name":"Jean Témerson","idIMDB":"nm0879400","filmographies":[{"section":"Actor","filmography":[{"title":"Diabolique","year":" 1955","remarks":["Le garçon d'hôtel (as Jean Temerson)"],"imdbid":"tt0046911"},{"title":"A Woman of Evil","year":" 1954","remarks":["L'aubergiste de 'La belle étoile' (as Jean Temmerson)"],"imdbid":"tt0047401"},{"title":"Flesh and the Woman","year":" 1954","remarks":null,"imdbid":"tt0047044"},{"title":"The Count of Monte Cristo","year":" 1954","remarks":null,"imdbid":"tt0046415"},{"title":"Le cap de l'espérance","year":" 1951","remarks":null,"imdbid":"tt0135178"},{"title":"Coq en pâte","year":" 1951","remarks":null,"imdbid":"tt0156425"},{"title":"Le gang des tractions-arrière","year":" 1950","remarks":null,"imdbid":"tt0157685"},{"title":"Tête blonde","year":" 1950","remarks":null,"imdbid":"tt0191599"},{"title":"Véronique","year":" 1950","remarks":null,"imdbid":"tt0202083"},{"title":"L'atomique Monsieur Placido","year":" 1950","remarks":["Un maître d'hôtel (as Temerson)"],"imdbid":"tt0197255"},{"title":"Sans tambour ni trompette","year":" 1950","remarks":null,"imdbid":"tt0200086"},{"title":"La belle que voilà","year":" 1950","remarks":["Théophile (as Témerson)"],"imdbid":"tt0139062"},{"title":"Dominique","year":" 1950","remarks":null,"imdbid":"tt0156482"},{"title":"Miquette et sa mère","year":" 1950","remarks":["Saint-Giron (as Temerson)"],"imdbid":"tt0042736"},{"title":"Manon","year":" 1949","remarks":["Le portier du 'Magic' (as Témerson)"],"imdbid":"tt0041634"},{"title":"Fantômas contre Fantômas","year":" 1949","remarks":["Le président du consortium du marché noir (as Témerson)"],"imdbid":"tt0143247"},{"title":"Kean","year":" 1949","remarks":["(TV Movie)"],"imdbid":"tt1818387"},{"title":"The Cupboard Was Bare","year":" 1948","remarks":["Le deuxième habitué (as Temerson)"],"imdbid":"tt0040114"},{"title":"Une mort sans importance","year":" 1948","remarks":null,"imdbid":"tt0447508"},{"title":"Si jeunesse savait...","year":" 1948","remarks":null,"imdbid":"tt0138803"},{"title":"Cargaison clandestine","year":" 1947","remarks":null,"imdbid":"tt0204183"},{"title":"Coeur de coq","year":" 1946","remarks":["Stanislas Pugilaskoff (as Jean Temerson)"],"imdbid":"tt0171186"},{"title":"L'ennemi sans visage","year":" 1946","remarks":null,"imdbid":"tt0136798"},{"title":"On ne meurt pas comme ça","year":" 1946","remarks":null,"imdbid":"tt0194212"},{"title":"Une femme coupée en morceaux","year":" 1946","remarks":null,"imdbid":"tt0289595"},{"title":"Les malheurs de Sophie","year":" 1946","remarks":null,"imdbid":"tt0202460"},{"title":"Soyez les bienvenus","year":" 1942","remarks":null,"imdbid":"tt0195297"},{"title":"Volpone ou l'amour de l'or","year":" 1941","remarks":["(as Témerson)"],"imdbid":"tt0033229"},{"title":"Monsieur Hector","year":" 1940","remarks":["Le Baron Grondin (as Témerson)"],"imdbid":"tt0161825"},{"title":"Le président Haudecoeur","year":" 1940","remarks":["Capet (as Temerson)"],"imdbid":"tt0198935"},{"title":"Le Danube bleu","year":" 1940","remarks":["Alexander (as Temerson)"],"imdbid":"tt0203436"},{"title":"Personal Column","year":" 1939","remarks":null,"imdbid":"tt0031800"},{"title":"Le bois sacré","year":" 1939","remarks":["L'huissier (as Témerson)"],"imdbid":"tt0175492"},{"title":"Monsieur Brotonneau","year":" 1939","remarks":null,"imdbid":"tt0239659"},{"title":"Berlingot et Cie","year":" 1939","remarks":["Donadieu - un homme aux idées bien arrêtées (as Temerson)"],"imdbid":"tt0149843"},{"title":"Mon oncle et mon curé","year":" 1939","remarks":null,"imdbid":"tt0192326"},{"title":"Les cinq sous de Lavarède","year":" 1939","remarks":["Tartinovitch (as Temerson)"],"imdbid":"tt0031157"},{"title":"Les gangsters du château d'If","year":" 1939","remarks":["Papalouche (as Temerson)"],"imdbid":"tt0193970"},{"title":"Raphaël le tatoué","year":" 1939","remarks":["Monsieur Chromo (as Témerson)"],"imdbid":"tt0160737"},{"title":"Le capitaine Benoît","year":" 1938","remarks":["Tripoff, le touriste (as Témerson)"],"imdbid":"tt0171150"},{"title":"Chess Player","year":" 1938","remarks":["(as Temerson)"],"imdbid":"tt0030292"},{"title":"Prince de mon coeur","year":" 1938","remarks":null,"imdbid":"tt0193432"},{"title":"Le révolté","year":" 1938","remarks":["Blotaque (as Jean Temerson)"],"imdbid":"tt0191414"},{"title":"Bargekeepers Daughter","year":" 1938","remarks":null,"imdbid":"tt0031010"},{"title":"La piste du sud","year":" 1938","remarks":["Chailloux (as Témerson)"],"imdbid":"tt0160667"},{"title":"S.O.S. Mediterranean","year":" 1938","remarks":null,"imdbid":"tt0190961"},{"title":"Barnabé","year":" 1938","remarks":null,"imdbid":"tt0175468"},{"title":"Ramuntcho","year":" 1938","remarks":["Salaberry (as Témerson)"],"imdbid":"tt0160734"},{"title":"Les deux combinards","year":" 1938","remarks":null,"imdbid":"tt0191084"},{"title":"The Alibi","year":" 1937","remarks":["Jojo, l'ami de Dany (as Temerson)"],"imdbid":"tt0028567"},{"title":"The Messenger","year":" 1937","remarks":["Le maître d'hôtel (uncredited)"],"imdbid":"tt0029235"},{"title":"Boulot aviateur","year":" 1937","remarks":null,"imdbid":"tt0196402"},{"title":"La chaste Suzanne","year":" 1937","remarks":["Alexis (as Temerson)"],"imdbid":"tt0194749"},{"title":"Champs-Elysees","year":" 1937","remarks":null,"imdbid":"tt0195212"},{"title":"Blanchette","year":" 1937","remarks":null,"imdbid":"tt0175487"},{"title":"Pépé le Moko","year":" 1937","remarks":["Gravère (as Temerson)"],"imdbid":"tt0029453"},{"title":"With a Smile","year":" 1936","remarks":["Cam (uncredited)"],"imdbid":"tt0027321"},{"title":"L'amant de Madame Vidal","year":" 1936","remarks":null,"imdbid":"tt0191777"}]}]}]},"about":{"version":"2.26.6","serverTime":"2017/01/15 06:38:34"}}